{
    "Titles": {
        "Comments": "Comentarios",
        "CreationDate": "Fecha de creación",
        "CustomsInformation": "Información aduanera",
        "EndDate": "Fecha de finalización",
        "Id": "Id",
        "Location": "Ubicación",
        "Quantity": "Cantidad",
        "RateActivityName": "Actividad",
        "RateClientName": "Cliente",
        "RateProductName": "Producto",
        "SectorName": "Área",
        "SelectedEmployees": "Operarios",
        "SelectedNovelties": "Novedades",
        "UnifiedVehicleTypeName": "Tipo de vehículo",
        "VehicleNumber": "Placas del vehículo"
    }
}
